{
    "Version": "1.1",
    "Data": {
        "Source": "c:\\users\\tadgh admin\\source\\repos\\xsltpp\\xsltpp\\lib.cppm",
        "ProvidedModule": "lib",
        "ImportedModules": [
            "Debug"
        ],
        "ImportedHeaderUnits": [
            "C:\\Program Files\\Microsoft Visual Studio\\2022\\Community\\VC\\Tools\\MSVC\\14.31.31103\\include\\iostream",
            "C:\\Program Files\\Microsoft Visual Studio\\2022\\Community\\VC\\Tools\\MSVC\\14.31.31103\\include\\string",
            "C:\\Program Files\\Microsoft Visual Studio\\2022\\Community\\VC\\Tools\\MSVC\\14.31.31103\\include\\vector"
        ]
    }
}